README.md
setup.py
Proximity_Forest_dtw.egg-info/PKG-INFO
Proximity_Forest_dtw.egg-info/SOURCES.txt
Proximity_Forest_dtw.egg-info/dependency_links.txt
Proximity_Forest_dtw.egg-info/requires.txt
Proximity_Forest_dtw.egg-info/top_level.txt
application/AppRunner.py
application/PFApplication.py
application/PFApplicationTest.py
application/PFSktime.py
application/WindowComparator.py
application/__init__.py
application/crossvalidation.py
core/AppContext.py
core/ExperimentRunner.py
core/FileReader.py
core/PFResult.py
core/TreeStatCollector.py
core/__init__.py
dataStructures/ListDataset.py
dataStructures/__init__.py
distance/DistanceMeasure.py
distance/__init__.py
proximity_forest_DTW.egg-info/PKG-INFO
proximity_forest_DTW.egg-info/SOURCES.txt
proximity_forest_DTW.egg-info/dependency_links.txt
proximity_forest_DTW.egg-info/top_level.txt
proximity_forest_dtw.egg-info/PKG-INFO
proximity_forest_dtw.egg-info/SOURCES.txt
proximity_forest_dtw.egg-info/dependency_links.txt
proximity_forest_dtw.egg-info/requires.txt
proximity_forest_dtw.egg-info/top_level.txt
trees/Node.py
trees/ProximityForest.py
trees/ProximityTree.py
trees/Splitter.py
trees/__init__.py