Metadata-Version: 1.2
Name: Proximity-Forest-dtw
Version: 1.1
Summary: Proximity Forest Classifier using DTW distance measure
Home-page: https://github.com/moradisten/ProximityForests-python
Author: Moradisten
Author-email: moradabaz@gmail.com
License: UNKNOWN
Keywords: time series classification
Platform: UNKNOWN
Requires-Python: >=3.6
